{"modelName":"consoleservices_Access_Events","displayName":"consoleservices Access Events","description":"This models data from the console-services access logs","objectSummary":{"Event-Based":2,"Transaction-Based":0,"Search-Based":0},"objects":[{"objectName":"consoleservices_Access_Event","displayName":"consoleservices Access Event","parentName":"BaseEvent","fields":[{"fieldName":"bytes","owner":"consoleservices_Access_Event","type":"number","fieldSearch":"","required":false,"multivalue":false,"hidden":false,"editable":true,"displayName":"bytes","comment":""},{"fieldName":"clientip","owner":"consoleservices_Access_Event","type":"string","fieldSearch":"","required":false,"multivalue":false,"hidden":false,"editable":true,"displayName":"clientip","comment":""},{"fieldName":"level","owner":"consoleservices_Access_Event","type":"string","fieldSearch":"","required":false,"multivalue":false,"hidden":false,"editable":true,"displayName":"level","comment":""},{"fieldName":"status","owner":"consoleservices_Access_Event","type":"number","fieldSearch":"","required":false,"multivalue":false,"hidden":false,"editable":true,"displayName":"status","comment":""},{"fieldName":"uri","owner":"consoleservices_Access_Event","type":"string","fieldSearch":"","required":false,"multivalue":false,"hidden":false,"editable":true,"displayName":"uri","comment":""},{"fieldName":"uri_domain","owner":"consoleservices_Access_Event","type":"string","fieldSearch":"","required":false,"multivalue":false,"hidden":false,"editable":true,"displayName":"uri_domain","comment":""},{"fieldName":"uri_path","owner":"consoleservices_Access_Event","type":"string","fieldSearch":"","required":false,"multivalue":false,"hidden":false,"editable":true,"displayName":"uri_path","comment":""},{"fieldName":"uri_query","owner":"consoleservices_Access_Event","type":"string","fieldSearch":"","required":false,"multivalue":false,"hidden":false,"editable":true,"displayName":"uri_query","comment":""},{"fieldName":"user","owner":"consoleservices_Access_Event","type":"string","fieldSearch":"","required":false,"multivalue":false,"hidden":false,"editable":true,"displayName":"user","comment":""},{"fieldName":"root","owner":"consoleservices_Access_Event","type":"string","fieldSearch":"","required":false,"multivalue":false,"hidden":false,"editable":true,"displayName":"root","comment":""},{"fieldName":"timeendpos","owner":"consoleservices_Access_Event","type":"number","fieldSearch":"","required":false,"multivalue":false,"hidden":false,"editable":true,"displayName":"timeendpos","comment":""},{"fieldName":"timestartpos","owner":"consoleservices_Access_Event","type":"number","fieldSearch":"","required":false,"multivalue":false,"hidden":false,"editable":true,"displayName":"timestartpos","comment":""},{"fieldName":"other","owner":"consoleservices_Access_Event","type":"string","fieldSearch":"","required":false,"multivalue":false,"hidden":true,"editable":true,"displayName":"other","comment":""},{"fieldName":"_time","owner":"BaseEvent","type":"timestamp","fieldSearch":"","required":false,"multivalue":false,"hidden":false,"editable":true,"displayName":"_time","comment":""},{"fieldName":"host","owner":"BaseEvent","type":"string","fieldSearch":"","required":false,"multivalue":false,"hidden":false,"editable":true,"displayName":"host","comment":""},{"fieldName":"source","owner":"BaseEvent","type":"string","fieldSearch":"","required":false,"multivalue":false,"hidden":false,"editable":true,"displayName":"source","comment":""},{"fieldName":"sourcetype","owner":"BaseEvent","type":"string","fieldSearch":"","required":false,"multivalue":false,"hidden":false,"editable":true,"displayName":"sourcetype","comment":""}],"calculations":[{"outputFields":[{"fieldName":"response_time","owner":"consoleservices_Access_Event","type":"number","fieldSearch":"","required":false,"multivalue":false,"hidden":false,"editable":true,"displayName":"response_time","comment":""},{"fieldName":"remote_host","owner":"consoleservices_Access_Event","type":"string","fieldSearch":"","required":false,"multivalue":false,"hidden":false,"editable":true,"displayName":"remote_host","comment":""}],"inputField":"other","calculationID":"wvrbpk31xqc","owner":"consoleservices_Access_Event","editable":true,"comment":"","calculationType":"Rex","expression":"(?<response_time>^\\d+)\\s(?<remote_host>.*)"}],"constraints":[{"search":"index=puppet-enterprise sourcetype=consoleservices_access","owner":"consoleservices_Access_Event"}],"lineage":"consoleservices_Access_Event"},{"objectName":"consoleservices_Access_Errors","displayName":"consoleservices Access Errors","parentName":"consoleservices_Access_Event","fields":[{"fieldName":"bytes","owner":"consoleservices_Access_Event","type":"number","fieldSearch":"","required":false,"multivalue":false,"hidden":false,"editable":true,"displayName":"bytes","comment":""},{"fieldName":"clientip","owner":"consoleservices_Access_Event","type":"string","fieldSearch":"","required":false,"multivalue":false,"hidden":false,"editable":true,"displayName":"clientip","comment":""},{"fieldName":"level","owner":"consoleservices_Access_Event","type":"string","fieldSearch":"","required":false,"multivalue":false,"hidden":false,"editable":true,"displayName":"level","comment":""},{"fieldName":"status","owner":"consoleservices_Access_Event","type":"number","fieldSearch":"","required":false,"multivalue":false,"hidden":false,"editable":true,"displayName":"status","comment":""},{"fieldName":"uri","owner":"consoleservices_Access_Event","type":"string","fieldSearch":"","required":false,"multivalue":false,"hidden":false,"editable":true,"displayName":"uri","comment":""},{"fieldName":"uri_domain","owner":"consoleservices_Access_Event","type":"string","fieldSearch":"","required":false,"multivalue":false,"hidden":false,"editable":true,"displayName":"uri_domain","comment":""},{"fieldName":"uri_path","owner":"consoleservices_Access_Event","type":"string","fieldSearch":"","required":false,"multivalue":false,"hidden":false,"editable":true,"displayName":"uri_path","comment":""},{"fieldName":"uri_query","owner":"consoleservices_Access_Event","type":"string","fieldSearch":"","required":false,"multivalue":false,"hidden":false,"editable":true,"displayName":"uri_query","comment":""},{"fieldName":"user","owner":"consoleservices_Access_Event","type":"string","fieldSearch":"","required":false,"multivalue":false,"hidden":false,"editable":true,"displayName":"user","comment":""},{"fieldName":"root","owner":"consoleservices_Access_Event","type":"string","fieldSearch":"","required":false,"multivalue":false,"hidden":false,"editable":true,"displayName":"root","comment":""},{"fieldName":"timeendpos","owner":"consoleservices_Access_Event","type":"number","fieldSearch":"","required":false,"multivalue":false,"hidden":false,"editable":true,"displayName":"timeendpos","comment":""},{"fieldName":"timestartpos","owner":"consoleservices_Access_Event","type":"number","fieldSearch":"","required":false,"multivalue":false,"hidden":false,"editable":true,"displayName":"timestartpos","comment":""},{"fieldName":"other","owner":"consoleservices_Access_Event","type":"string","fieldSearch":"","required":false,"multivalue":false,"hidden":true,"editable":true,"displayName":"other","comment":""},{"fieldName":"_time","owner":"BaseEvent","type":"timestamp","fieldSearch":"","required":false,"multivalue":false,"hidden":false,"editable":true,"displayName":"_time","comment":""},{"fieldName":"host","owner":"BaseEvent","type":"string","fieldSearch":"","required":false,"multivalue":false,"hidden":false,"editable":true,"displayName":"host","comment":""},{"fieldName":"source","owner":"BaseEvent","type":"string","fieldSearch":"","required":false,"multivalue":false,"hidden":false,"editable":true,"displayName":"source","comment":""},{"fieldName":"sourcetype","owner":"BaseEvent","type":"string","fieldSearch":"","required":false,"multivalue":false,"hidden":false,"editable":true,"displayName":"sourcetype","comment":""}],"calculations":[],"constraints":[{"search":"status=4*","owner":"consoleservices_Access_Event.consoleservices_Access_Errors"}],"lineage":"consoleservices_Access_Event.consoleservices_Access_Errors"}],"objectNameList":["consoleservices_Access_Event","consoleservices_Access_Errors"]}