<form>
  <label>Console Services Overview</label>
  <description>This dashboard displays performance and usage data around PE console-services requests</description>
  <fieldset submitButton="false">
    <input type="time" token="field1" searchWhenChanged="true">
      <label></label>
      <default>
        <earliest>-24h@h</earliest>
        <latest>now</latest>
      </default>
    </input>
  </fieldset>
  <row>
    <panel>
      <chart>
        <title>Average HTTP response times for Console Services</title>
        <search>
          <query>| pivot consoleservices_Access_Events consoleservices_Access_Event avg(response_time) AS "Average of response_time" SPLITROW _time AS _time PERIOD auto SORT 100 _time ROWSUMMARY 0 COLSUMMARY 0 NUMCOLS 0 SHOWOTHER 1</query>
          <earliest>$field1.earliest$</earliest>
          <latest>$field1.latest$</latest>
        </search>
        <option name="charting.axisY2.enabled">0</option>
        <option name="charting.axisLabelsX.majorLabelStyle.overflowMode">ellipsisNone</option>
        <option name="charting.axisLabelsX.majorLabelStyle.rotation">0</option>
        <option name="charting.axisTitleX.visibility">visible</option>
        <option name="charting.axisTitleY.visibility">visible</option>
        <option name="charting.axisTitleY2.visibility">visible</option>
        <option name="charting.axisX.scale">linear</option>
        <option name="charting.axisY.scale">linear</option>
        <option name="charting.axisY2.scale">inherit</option>
        <option name="charting.chart">line</option>
        <option name="charting.chart.bubbleMaximumSize">50</option>
        <option name="charting.chart.bubbleMinimumSize">10</option>
        <option name="charting.chart.bubbleSizeBy">area</option>
        <option name="charting.chart.nullValueMode">gaps</option>
        <option name="charting.chart.showDataLabels">none</option>
        <option name="charting.chart.sliceCollapsingThreshold">0.01</option>
        <option name="charting.chart.stackMode">default</option>
        <option name="charting.chart.style">shiny</option>
        <option name="charting.drilldown">all</option>
        <option name="charting.layout.splitSeries">0</option>
        <option name="charting.layout.splitSeries.allowIndependentYRanges">0</option>
        <option name="charting.legend.labelStyle.overflowMode">ellipsisMiddle</option>
        <option name="charting.legend.placement">none</option>
      </chart>
    </panel>
  </row>
  <row>
    <panel>
      <chart>
        <title>Request size and response time comparison</title>
        <search>
          <query>| pivot consoleservices_Access_Events consoleservices_Access_Event max(bytes) AS "Max of bytes" max(response_time) AS "Max of response_time" SPLITROW _time AS _time PERIOD auto SORT 100 _time ROWSUMMARY 0 COLSUMMARY 0 NUMCOLS 0 SHOWOTHER 1</query>
          <earliest>$field1.earliest$</earliest>
          <latest>$field1.latest$</latest>
        </search>
        <option name="charting.axisY2.enabled">0</option>
        <option name="charting.axisLabelsX.majorLabelStyle.overflowMode">ellipsisNone</option>
        <option name="charting.axisLabelsX.majorLabelStyle.rotation">0</option>
        <option name="charting.axisTitleX.visibility">visible</option>
        <option name="charting.axisTitleY.visibility">visible</option>
        <option name="charting.axisTitleY2.visibility">visible</option>
        <option name="charting.axisX.scale">linear</option>
        <option name="charting.axisY.scale">linear</option>
        <option name="charting.axisY2.scale">inherit</option>
        <option name="charting.chart">scatter</option>
        <option name="charting.chart.bubbleMaximumSize">50</option>
        <option name="charting.chart.bubbleMinimumSize">10</option>
        <option name="charting.chart.bubbleSizeBy">area</option>
        <option name="charting.chart.nullValueMode">gaps</option>
        <option name="charting.chart.showDataLabels">none</option>
        <option name="charting.chart.sliceCollapsingThreshold">0.01</option>
        <option name="charting.chart.stackMode">default</option>
        <option name="charting.chart.style">shiny</option>
        <option name="charting.drilldown">all</option>
        <option name="charting.layout.splitSeries">0</option>
        <option name="charting.layout.splitSeries.allowIndependentYRanges">0</option>
        <option name="charting.legend.labelStyle.overflowMode">ellipsisMiddle</option>
        <option name="charting.legend.placement">right</option>
      </chart>
    </panel>
  </row>
  <row>
    <panel>
      <table>
        <title>Request errors by client</title>
        <search>
          <query>| pivot consoleservices_Access_Events consoleservices_Access_Errors count(consoleservices_Access_Errors) AS "Count of consoleservices Access Errors" SPLITROW remote_host AS "Client IP" SPLITROW uri AS uri FILTER remote_host isNot "-" TOP 100 count(consoleservices_Access_Errors) ROWSUMMARY 0 COLSUMMARY 0 NUMCOLS 0 SHOWOTHER 1</query>
          <earliest>$field1.earliest$</earliest>
          <latest>$field1.latest$</latest>
        </search>
        <option name="wrap">true</option>
        <option name="rowNumbers">false</option>
        <option name="dataOverlayMode">none</option>
        <option name="drilldown">cell</option>
        <option name="count">10</option>
      </table>
    </panel>
  </row>
  <row>
    <panel>
      <table>
        <title>Authenticated RBAC users</title>
        <search>
          <query>| pivot consoleservices_Events consoleservices_RBAC_Events count(consoleservices_RBAC_Events) AS "Number of logins" SPLITROW user AS "Authenticated Users" SPLITROW host AS "Console Host" SORT 100 user ROWSUMMARY 0 COLSUMMARY 0 NUMCOLS 0 SHOWOTHER 1</query>
          <earliest>-24h@h</earliest>
          <latest>now</latest>
        </search>
        <option name="wrap">true</option>
        <option name="rowNumbers">false</option>
        <option name="dataOverlayMode">none</option>
        <option name="drilldown">cell</option>
        <option name="count">10</option>
      </table>
    </panel>
    <panel>
      <chart>
        <title>Failed RBAC authentications over time</title>
        <search>
          <query>| pivot consoleservices_Events consoleservices_RBAC_Events count(consoleservices_RBAC_Events) AS "Failed authentication attempts" SPLITROW _time AS _time PERIOD auto FILTER log_message is "Authentication failed." SORT 100 _time ROWSUMMARY 0 COLSUMMARY 0 NUMCOLS 0 SHOWOTHER 1</query>
          <earliest>$field1.earliest$</earliest>
          <latest>$field1.latest$</latest>
        </search>
        <option name="charting.axisY2.enabled">0</option>
        <option name="charting.axisLabelsX.majorLabelStyle.overflowMode">ellipsisNone</option>
        <option name="charting.axisLabelsX.majorLabelStyle.rotation">0</option>
        <option name="charting.axisTitleX.visibility">visible</option>
        <option name="charting.axisTitleY.visibility">visible</option>
        <option name="charting.axisTitleY2.visibility">visible</option>
        <option name="charting.axisX.scale">linear</option>
        <option name="charting.axisY.scale">linear</option>
        <option name="charting.axisY2.scale">inherit</option>
        <option name="charting.chart">column</option>
        <option name="charting.chart.bubbleMaximumSize">50</option>
        <option name="charting.chart.bubbleMinimumSize">10</option>
        <option name="charting.chart.bubbleSizeBy">area</option>
        <option name="charting.chart.nullValueMode">gaps</option>
        <option name="charting.chart.showDataLabels">none</option>
        <option name="charting.chart.sliceCollapsingThreshold">0.01</option>
        <option name="charting.chart.stackMode">default</option>
        <option name="charting.chart.style">shiny</option>
        <option name="charting.drilldown">all</option>
        <option name="charting.layout.splitSeries">0</option>
        <option name="charting.layout.splitSeries.allowIndependentYRanges">0</option>
        <option name="charting.legend.labelStyle.overflowMode">ellipsisMiddle</option>
        <option name="charting.legend.placement">none</option>
      </chart>
    </panel>
  </row>
</form>